smartfs_tools/__init__.py
smartfs_tools/base.py
smartfs_tools/script.py
smartfs_tools/smart.py
smartfs_tools/smart_high.py
smartfs_tools-0.4.0.dist-info/METADATA
smartfs_tools-0.4.0.dist-info/WHEEL
smartfs_tools-0.4.0.dist-info/entry_points.txt
smartfs_tools-0.4.0.dist-info/RECORD
